wkmake/__init__.py
wkmake/make.py
wkmake/pkg_info.py
wkmake/utils.py
wkmake/clitools/__init__.py
wkmake/clitools/cli.py
wkmake/data/example/wkmake.yaml
wkmake/data/example/example-package/.gitignore
wkmake/data/example/example-package/LICENSE
wkmake/data/example/example-package/README.md
wkmake/data/example/example-package/build.bat
wkmake/data/example/example-package/build.sh
wkmake/data/example/example-package/gitinit.bat
wkmake/data/example/example-package/gitinit.sh
wkmake/data/example/example-package/install.sh
wkmake/data/example/example-package/setup.py
wkmake/data/example/example-package/setup.sh
wkmake/data/example/example-package/update.bat
wkmake/data/example/example-package/update.sh
wkmake/data/example/example-package/upgit.bat
wkmake/data/example/example-package/upgit.sh
wkmake/data/example/example-package/version.txt
wkmake/data/example/example-package/wkmake.json
wkmake/data/templates/wkmake.yaml
wkmake/data/templates/python_package/.gitignore
wkmake/data/templates/python_package/LICENSE
wkmake/data/templates/python_package/README.md
wkmake/data/templates/python_package/build.bat
wkmake/data/templates/python_package/build.sh
wkmake/data/templates/python_package/gitinit.bat
wkmake/data/templates/python_package/gitinit.sh
wkmake/data/templates/python_package/install.sh
wkmake/data/templates/python_package/setup.py
wkmake/data/templates/python_package/setup.sh
wkmake/data/templates/python_package/update.bat
wkmake/data/templates/python_package/update.sh
wkmake/data/templates/python_package/upgit.bat
wkmake/data/templates/python_package/upgit.sh
wkmake/data/templates/python_package/version.txt
wkmake-0.0.6.2.dist-info/LICENSE
wkmake-0.0.6.2.dist-info/METADATA
wkmake-0.0.6.2.dist-info/WHEEL
wkmake-0.0.6.2.dist-info/entry_points.txt
wkmake-0.0.6.2.dist-info/top_level.txt
wkmake-0.0.6.2.dist-info/RECORD
